{"cameraMode":{"drawMode":0,"name":"Shaded","section":"Shading Mode"},"sceneLighting":true,"audioPlay":false,"sceneViewState":{"m_AlwaysRefresh":false,"showFog":true,"showSkybox":true,"showFlares":true,"showImageEffects":true,"showParticleSystems":true,"showVisualEffectGraphs":true,"m_FxEnabled":true},"in2DMode":false,"pivot":{"x":5.422537326812744,"y":-17.34955596923828,"z":31.13022232055664},"rotation":{"x":-0.26327526569366457,"y":-0.0426173061132431,"z":0.01472779456526041,"w":-0.9641082882881165},"size":20.00494956970215,"orthographic":false}